[
  {
    "title": "Video 1",
    "thumbnail": "",
    "url": "https://www.dropbox.com/scl/fi/rb0kmd5p6gwwymfpcwpdn/video1.mp4?rlkey=oqmls8jknv3nlk7vrkqgwyuzs&raw=1"
  },
  {
    "title": "Video 2",
    "thumbnail": "",
    "url": "https://www.dropbox.com/scl/fi/emkpk4gi60ndxwfmjwp54/video2.mp4?rlkey=5o4s2wkzakj3p7wsg2g7zjpbk&raw=1"
  },
  {
    "title": "Video 3",
    "thumbnail": "",
    "url": "https://www.dropbox.com/scl/fi/i3wjoh7aqxg1s6g1btc1e/video3.mp4?rlkey=ds5mqvamh2x5in9w0759esy4c&raw=1"
  },
  {
    "title": "Video 4",
    "thumbnail": "",
    "url": "https://www.dropbox.com/scl/fi/ziokuu9t674rclarqx2fy/video4.mp4?rlkey=skj0yn2rny59a3iskfae1iyli&raw=1"
  },
  {
    "title": "Video 5",
    "thumbnail": "",
    "url": "https://www.dropbox.com/scl/fi/mc9fyh6cu27z6jcf2jqgc/video5.mp4?rlkey=cl3ss3eojjhfdqcv2p45wgnqk&raw=1"
  },
  {
    "title": "Zindagi Na Milegi Dobara (2011)",
    "thumbnail": "",
    "url": "https://www.dropbox.com/scl/fi/bcvsa22x1q8ch5ujvrcw9/Zindagi_Na_Milegi_Dobara.mp4?rlkey=r6i0vvgcdh3wsidvvoi1ftg24&raw=1"
  }
]
